xivlodestone/__init__.py
xivlodestone/enums.py
xivlodestone/errors.py
xivlodestone/lodestone.py
xivlodestone/models.py
xivlodestone/py.typed
xivlodestone/scraper.py
xivlodestone-1.0.0b1.dist-info/METADATA
xivlodestone-1.0.0b1.dist-info/WHEEL
xivlodestone-1.0.0b1.dist-info/licenses/LICENSE.md
xivlodestone-1.0.0b1.dist-info/RECORD
