Metadata-Version: 2.4
Name: xivlodestone
Version: 1.0.0b1
Summary: xivlodestone is a Python library that interacts with the FFXIV Lodestone website.
Project-URL: Homepage, https://github.com/RikuPy/xivlodestone
Project-URL: Issues, https://github.com/RikuPy/xivlodestone/issues
Author: RikuPy
License-Expression: MIT
License-File: LICENSE.md
Classifier: Development Status :: 4 - Beta
Classifier: Intended Audience :: Developers
Classifier: License :: OSI Approved :: MIT License
Classifier: Programming Language :: Python :: 3
Classifier: Programming Language :: Python :: 3.11
Classifier: Programming Language :: Python :: 3.12
Classifier: Programming Language :: Python :: 3.13
Classifier: Topic :: Games/Entertainment
Classifier: Topic :: Internet :: WWW/HTTP
Classifier: Topic :: Software Development :: Libraries
Classifier: Topic :: Software Development :: Libraries :: Python Modules
Classifier: Typing :: Typed
Requires-Python: >=3.11
Requires-Dist: aiohttp>=3.11.16
Requires-Dist: beautifulsoup4>=4.13.4
Requires-Dist: msgspec>=0.19.0
